sir3stoolkit/__init__.py
sir3stoolkit/core/__init__.py
sir3stoolkit/core/wrapper.py
sir3stoolkit/lib/Sir3S_Toolkit.dll
sir3stoolkit/mantle/__init__.py
sir3stoolkit/mantle/advanced_operations.py
sir3stoolkit/mantle/alternative_models.py
sir3stoolkit/mantle/dataframes.py
sir3stoolkit/mantle/mantle.py
sir3stoolkit/mantle/plotting.py
sir3stoolkit-90.15.9.dist-info/licenses/LICENSE
test/minimal_test.py
sir3stoolkit-90.15.9.dist-info/METADATA
sir3stoolkit-90.15.9.dist-info/WHEEL
sir3stoolkit-90.15.9.dist-info/top_level.txt
sir3stoolkit-90.15.9.dist-info/RECORD
