Metadata-Version: 2.4
Name: sir3stoolkit
Version: 90.15.9
Summary: SIR3S Toolkit
Author-email: 3S Consult GmbH <sir3stoolkit@3sconsult.de>
License: MIT
Project-URL: Documentation, https://3sconsult.github.io/sir3stoolkit
Project-URL: Source, https://github.com/3SConsult/sir3stoolkit
Project-URL: Repository, https://github.com/3SConsult/sir3stoolkit.git
Project-URL: Issues, https://github.com/3SConsult/sir3stoolkit/issues
Project-URL: Download, https://pypi.org/project/sir3stoolkit/#files
Keywords: Python,3S,SIR 3S,SirGraf,SirCalc,3S Consult,network,pipeline,analysis,automation,engineering,simulation,hydraulics,gas,water,district heating,oil
Classifier: Development Status :: 5 - Production/Stable
Classifier: Environment :: Console
Classifier: Framework :: Jupyter
Classifier: Intended Audience :: Developers
Classifier: Intended Audience :: Information Technology
Classifier: Intended Audience :: Science/Research
Classifier: License :: OSI Approved :: MIT License
Classifier: Operating System :: Microsoft :: Windows
Classifier: Programming Language :: Python
Classifier: Programming Language :: Python :: 3.12
Classifier: Topic :: Scientific/Engineering
Requires-Python: >=3.12
License-File: LICENSE
Requires-Dist: numpy
Requires-Dist: pythonnet
Provides-Extra: dev
Requires-Dist: pytest; extra == "dev"
Requires-Dist: flake8; extra == "dev"
Requires-Dist: build; extra == "dev"
Requires-Dist: twine; extra == "dev"
Provides-Extra: sphinx
Requires-Dist: sphinx; extra == "sphinx"
Requires-Dist: sphinx_rtd_theme; extra == "sphinx"
Requires-Dist: nbsphinx; extra == "sphinx"
Requires-Dist: sphinx_copybutton; extra == "sphinx"
Requires-Dist: sphinx_togglebutton; extra == "sphinx"
Requires-Dist: pytoolconfig; extra == "sphinx"
Provides-Extra: mantle
Requires-Dist: pandas; extra == "mantle"
Requires-Dist: pandapipes; extra == "mantle"
Requires-Dist: shapely; extra == "mantle"
Requires-Dist: attrs; extra == "mantle"
Requires-Dist: pytoolconfig; extra == "mantle"
Requires-Dist: networkx; extra == "mantle"
Requires-Dist: matplotlib; extra == "mantle"
Requires-Dist: geopandas; extra == "mantle"
Dynamic: license-file
